{
   "Records":[
      {
         "eventVersion":"2.1",
         "eventSource":"aws:s3",
         "awsRegion":"us-east-2",
         "eventTime":"2023-03-23T03:35:39.706Z",
         "eventName":"ObjectCreated:Put",
         "userIdentity":
		 {
            "principalId":"AWS:AIDAYXRCTBTMSNGOAUT5C"
         },
         "requestParameters":{
            "sourceIPAddress":"186.178.170.145"
         },
         "responseElements":{
            "x-amz-request-id":"H6R57258YNWT5CM3",
            "x-amz-id-2":"SX0o2ZcGLFKngybCNy95HUadteUUmyanR/AeNcH13faDkolUKiWCNfx+j+ClPplftuINTiRbO4JWqP4BCrp9e8ZfoLYLCQpC"
         },
         "s3":
		 {
            "s3SchemaVersion":"1.0",
            "configurationId":"triggre-sqs",
            "bucket":
			{
               "name":"sa2-bucket",
               "ownerIdentity":
			   {
                  "principalId":"A1VHWHTGBUTKFO"
               },
               "arn":"arn:aws:s3:::sa2-bucket"
            },
            "object":
			{
               "key":"archivo7.json",
               "size":336129,
               "eTag":"6a79a8f5fe12c09b9eaa44aa97f1dc8f",
               "sequencer":"00641BC90AD31A733C"
            }
         }
      }
   ]
}